pyVmomi-stubs/METADATA.toml
pyVmomi-stubs/__init__.pyi
pyVmomi-stubs/vim/__init__.pyi
pyVmomi-stubs/vim/event.pyi
pyVmomi-stubs/vim/fault.pyi
pyVmomi-stubs/vim/option.pyi
pyVmomi-stubs/vim/view.pyi
pyVmomi-stubs/vmodl/__init__.pyi
pyVmomi-stubs/vmodl/fault.pyi
pyVmomi-stubs/vmodl/query.pyi
types_pyvmomi-8.0.0.5.dist-info/METADATA
types_pyvmomi-8.0.0.5.dist-info/WHEEL
types_pyvmomi-8.0.0.5.dist-info/top_level.txt
types_pyvmomi-8.0.0.5.dist-info/RECORD
